core/__init__.py
core/client.py
core/config.py
core/exceptions.py
core/server.py
main.py
prompts/__init__.py
tools/__init__.py
tools/info_tools.py
tools/search_tools.py
mcp_serp-2026.1.24.4.dist-info/METADATA
mcp_serp-2026.1.24.4.dist-info/WHEEL
mcp_serp-2026.1.24.4.dist-info/entry_points.txt
mcp_serp-2026.1.24.4.dist-info/licenses/LICENSE
mcp_serp-2026.1.24.4.dist-info/RECORD
